MANIFEST.in
README.rst
setup.py
dryxPython/.DS_Store
dryxPython/.coverage
dryxPython/.noseids
dryxPython/__init__.py
dryxPython/__init__.pyc
dryxPython/astrotools.py
dryxPython/astrotools.pyc
dryxPython/atelparser.py
dryxPython/atelparser.pyc
dryxPython/command_line.py
dryxPython/command_line.pyc
dryxPython/commonutils.py
dryxPython/commonutils.pyc
dryxPython/constants.py
dryxPython/constants.pyc
dryxPython/coverage.xml
dryxPython/csvtools.py
dryxPython/csvtools.pyc
dryxPython/fitstools.py
dryxPython/fitstools.pyc
dryxPython/logs.py
dryxPython/logs.pyc
dryxPython/mysql.py
dryxPython/mysql.pyc
dryxPython/nosetests.xml
dryxPython/plotting.py
dryxPython/plotting.pyc
dryxPython/projectsetup.py
dryxPython/projectsetup.pyc
dryxPython/randomdata.py
dryxPython/randomdata.pyc
dryxPython/regex.py
dryxPython/regex.pyc
dryxPython/setup.cfg
dryxPython/this_test.log
dryxPython/webcrawlers.py
dryxPython/webcrawlers.pyc
dryxPython/xmltools.py
dryxPython/xmltools.pyc
dryxPython.egg-info/PKG-INFO
dryxPython.egg-info/SOURCES.txt
dryxPython.egg-info/dependency_links.txt
dryxPython.egg-info/entry_points.txt
dryxPython.egg-info/not-zip-safe
dryxPython.egg-info/requires.txt
dryxPython.egg-info/top_level.txt
dryxPython/html_test_coverage_report/_Library_Python_2_7_site-packages_PyYAML-3_10-py2_7-macosx-10_8-intel_egg_yaml___init__.html
dryxPython/html_test_coverage_report/_Library_Python_2_7_site-packages_PyYAML-3_10-py2_7-macosx-10_8-intel_egg_yaml_composer.html
dryxPython/html_test_coverage_report/_Library_Python_2_7_site-packages_PyYAML-3_10-py2_7-macosx-10_8-intel_egg_yaml_constructor.html
dryxPython/html_test_coverage_report/_Library_Python_2_7_site-packages_PyYAML-3_10-py2_7-macosx-10_8-intel_egg_yaml_cyaml.html
dryxPython/html_test_coverage_report/_Library_Python_2_7_site-packages_PyYAML-3_10-py2_7-macosx-10_8-intel_egg_yaml_dumper.html
dryxPython/html_test_coverage_report/_Library_Python_2_7_site-packages_PyYAML-3_10-py2_7-macosx-10_8-intel_egg_yaml_emitter.html
dryxPython/html_test_coverage_report/_Library_Python_2_7_site-packages_PyYAML-3_10-py2_7-macosx-10_8-intel_egg_yaml_error.html
dryxPython/html_test_coverage_report/_Library_Python_2_7_site-packages_PyYAML-3_10-py2_7-macosx-10_8-intel_egg_yaml_events.html
