Metadata-Version: 1.1
Name: dryxPython
Version: 1.098
Summary: A collection of useful commonly used python modules
Home-page: https://github.com/thespacedoctor/dryxPython
Author: thespacedoctor
Author-email: nothingbutdave@gmail.com
License: MIT
Keywords: utilities dryx
Platform: UNKNOWN
Classifier: Development Status :: 4 - Beta
Classifier: License :: OSI Approved :: MIT License
Classifier: Programming Language :: Python :: 2.7
Classifier: Topic :: Utilities
